{"rowsInfo":["[Product].[Product Categories]"],"rows":[[{"name":"All Products","level":0}],[{"name":"Accessories","level":1}],[{"name":"Bike Racks","level":2}],[{"name":"Hitch Rack - 4-Bike","level":3}],[{"name":"Bike Stands","level":2}],[{"name":"All-Purpose Bike Stand","level":3}],[{"name":"Bottles and Cages","level":2}],[{"name":"Water Bottle - 30 oz.","level":3}],[{"name":"Mountain Bottle Cage","level":3}],[{"name":"Road Bottle Cage","level":3}],[{"name":"Cleaners","level":2}],[{"name":"Bike Wash - Dissolver","level":3}],[{"name":"Fenders","level":2}],[{"name":"Fender Set - Mountain","level":3}],[{"name":"Helmets","level":2}],[{"name":"Sport-100 Helmet, Red","level":3}],[{"name":"Sport-100 Helmet, Red","level":3}],[{"name":"Sport-100 Helmet, Red","level":3}],[{"name":"Sport-100 Helmet, Black","level":3}],[{"name":"Sport-100 Helmet, Black","level":3}],[{"name":"Sport-100 Helmet, Black","level":3}],[{"name":"Sport-100 Helmet, Blue","level":3}],[{"name":"Sport-100 Helmet, Blue","level":3}],[{"name":"Sport-100 Helmet, Blue","level":3}],[{"name":"Hydration Packs","level":2}],[{"name":"Hydration Pack - 70 oz.","level":3}],[{"name":"Locks","level":2}],[{"name":"Cable Lock","level":3}],[{"name":"Pumps","level":2}],[{"name":"Minipump","level":3}],[{"name":"Tires and Tubes","level":2}],[{"name":"Patch Kit\/8 Patches","level":3}],[{"name":"Mountain Tire Tube","level":3}],[{"name":"Road Tire Tube","level":3}],[{"name":"Touring Tire Tube","level":3}],[{"name":"LL Mountain Tire","level":3}],[{"name":"ML Mountain Tire","level":3}],[{"name":"HL Mountain Tire","level":3}],[{"name":"LL Road Tire","level":3}],[{"name":"ML Road Tire","level":3}],[{"name":"HL Road Tire","level":3}],[{"name":"Touring Tire","level":3}],[{"name":"Bikes","level":1}],[{"name":"Mountain Bikes","level":2}],[{"name":"Mountain-100 Silver, 38","level":3}],[{"name":"Mountain-100 Silver, 42","level":3}],[{"name":"Mountain-100 Silver, 44","level":3}],[{"name":"Mountain-100 Silver, 48","level":3}],[{"name":"Mountain-100 Black, 38","level":3}],[{"name":"Mountain-100 Black, 42","level":3}],[{"name":"Mountain-100 Black, 44","level":3}],[{"name":"Mountain-100 Black, 48","level":3}],[{"name":"Mountain-200 Silver, 38","level":3}],[{"name":"Mountain-200 Silver, 38","level":3}],[{"name":"Mountain-200 Silver, 42","level":3}],[{"name":"Mountain-200 Silver, 42","level":3}],[{"name":"Mountain-200 Silver, 46","level":3}],[{"name":"Mountain-200 Silver, 46","level":3}],[{"name":"Mountain-200 Black, 38","level":3}],[{"name":"Mountain-200 Black, 38","level":3}],[{"name":"Mountain-200 Black, 42","level":3}],[{"name":"Mountain-200 Black, 42","level":3}],[{"name":"Mountain-200 Black, 46","level":3}],[{"name":"Mountain-200 Black, 46","level":3}],[{"name":"Mountain-300 Black, 38","level":3}],[{"name":"Mountain-300 Black, 40","level":3}],[{"name":"Mountain-300 Black, 44","level":3}],[{"name":"Mountain-300 Black, 48","level":3}],[{"name":"Mountain-400-W Silver, 38","level":3}],[{"name":"Mountain-400-W Silver, 40","level":3}],[{"name":"Mountain-400-W Silver, 42","level":3}],[{"name":"Mountain-400-W Silver, 46","level":3}],[{"name":"Mountain-500 Silver, 40","level":3}],[{"name":"Mountain-500 Silver, 42","level":3}],[{"name":"Mountain-500 Silver, 44","level":3}],[{"name":"Mountain-500 Silver, 48","level":3}],[{"name":"Mountain-500 Silver, 52","level":3}],[{"name":"Mountain-500 Black, 40","level":3}],[{"name":"Mountain-500 Black, 42","level":3}],[{"name":"Mountain-500 Black, 44","level":3}],[{"name":"Mountain-500 Black, 48","level":3}],[{"name":"Mountain-500 Black, 52","level":3}],[{"name":"Road Bikes","level":2}],[{"name":"Road-150 Red, 62","level":3}],[{"name":"Road-150 Red, 44","level":3}],[{"name":"Road-150 Red, 48","level":3}],[{"name":"Road-150 Red, 52","level":3}],[{"name":"Road-150 Red, 56","level":3}],[{"name":"Road-450 Red, 58","level":3}],[{"name":"Road-450 Red, 60","level":3}],[{"name":"Road-450 Red, 44","level":3}],[{"name":"Road-450 Red, 48","level":3}],[{"name":"Road-450 Red, 52","level":3}],[{"name":"Road-650 Red, 58","level":3}],[{"name":"Road-650 Red, 58","level":3}],[{"name":"Road-650 Red, 60","level":3}],[{"name":"Road-650 Red, 60","level":3}],[{"name":"Road-650 Red, 62","level":3}],[{"name":"Road-650 Red, 62","level":3}],[{"name":"Road-650 Red, 44","level":3}],[{"name":"Road-650 Red, 44","level":3}],[{"name":"Road-650 Red, 48","level":3}],[{"name":"Road-650 Red, 48","level":3}],[{"name":"Road-650 Red, 52","level":3}],[{"name":"Road-650 Red, 52","level":3}],[{"name":"Road-650 Black, 58","level":3}],[{"name":"Road-650 Black, 58","level":3}],[{"name":"Road-650 Black, 60","level":3}],[{"name":"Road-650 Black, 60","level":3}],[{"name":"Road-650 Black, 62","level":3}],[{"name":"Road-650 Black, 62","level":3}],[{"name":"Road-650 Black, 44","level":3}],[{"name":"Road-650 Black, 44","level":3}],[{"name":"Road-650 Black, 48","level":3}],[{"name":"Road-650 Black, 48","level":3}],[{"name":"Road-650 Black, 52","level":3}],[{"name":"Road-650 Black, 52","level":3}],[{"name":"Road-250 Red, 44","level":3}],[{"name":"Road-250 Red, 48","level":3}],[{"name":"Road-250 Red, 52","level":3}],[{"name":"Road-250 Red, 58","level":3}],[{"name":"Road-250 Red, 58","level":3}],[{"name":"Road-250 Black, 44","level":3}],[{"name":"Road-250 Black, 44","level":3}],[{"name":"Road-250 Black, 48","level":3}],[{"name":"Road-250 Black, 48","level":3}],[{"name":"Road-250 Black, 52","level":3}],[{"name":"Road-250 Black, 52","level":3}],[{"name":"Road-250 Black, 58","level":3}],[{"name":"Road-250 Black, 58","level":3}],[{"name":"Road-550-W Yellow, 38","level":3}],[{"name":"Road-550-W Yellow, 38","level":3}],[{"name":"Road-550-W Yellow, 40","level":3}],[{"name":"Road-550-W Yellow, 40","level":3}],[{"name":"Road-550-W Yellow, 42","level":3}],[{"name":"Road-550-W Yellow, 42","level":3}],[{"name":"Road-550-W Yellow, 44","level":3}],[{"name":"Road-550-W Yellow, 44","level":3}],[{"name":"Road-550-W Yellow, 48","level":3}],[{"name":"Road-550-W Yellow, 48","level":3}],[{"name":"Road-350-W Yellow, 40","level":3}],[{"name":"Road-350-W Yellow, 42","level":3}],[{"name":"Road-350-W Yellow, 44","level":3}],[{"name":"Road-350-W Yellow, 48","level":3}],[{"name":"Road-750 Black, 58","level":3}],[{"name":"Road-750 Black, 44","level":3}],[{"name":"Road-750 Black, 48","level":3}],[{"name":"Road-750 Black, 52","level":3}],[{"name":"Touring Bikes","level":2}],[{"name":"Touring-2000 Blue, 60","level":3}],[{"name":"Touring-1000 Yellow, 46","level":3}],[{"name":"Touring-1000 Yellow, 50","level":3}],[{"name":"Touring-1000 Yellow, 54","level":3}],[{"name":"Touring-1000 Yellow, 60","level":3}],[{"name":"Touring-3000 Blue, 54","level":3}],[{"name":"Touring-3000 Blue, 58","level":3}],[{"name":"Touring-3000 Blue, 62","level":3}],[{"name":"Touring-3000 Yellow, 44","level":3}],[{"name":"Touring-3000 Yellow, 50","level":3}],[{"name":"Touring-3000 Yellow, 54","level":3}],[{"name":"Touring-3000 Yellow, 58","level":3}],[{"name":"Touring-3000 Yellow, 62","level":3}],[{"name":"Touring-1000 Blue, 46","level":3}],[{"name":"Touring-1000 Blue, 50","level":3}],[{"name":"Touring-1000 Blue, 54","level":3}],[{"name":"Touring-1000 Blue, 60","level":3}],[{"name":"Touring-2000 Blue, 46","level":3}],[{"name":"Touring-2000 Blue, 50","level":3}],[{"name":"Touring-2000 Blue, 54","level":3}],[{"name":"Touring-3000 Blue, 44","level":3}],[{"name":"Touring-3000 Blue, 50","level":3}],[{"name":"Clothing","level":1}],[{"name":"Bib-Shorts","level":2}],[{"name":"Men's Bib-Shorts, S","level":3}],[{"name":"Men's Bib-Shorts, M","level":3}],[{"name":"Men's Bib-Shorts, L","level":3}],[{"name":"Caps","level":2}],[{"name":"AWC Logo Cap","level":3}],[{"name":"AWC Logo Cap","level":3}],[{"name":"AWC Logo Cap","level":3}],[{"name":"Gloves","level":2}],[{"name":"Half-Finger Gloves, S","level":3}],[{"name":"Half-Finger Gloves, S","level":3}],[{"name":"Half-Finger Gloves, M","level":3}],[{"name":"Half-Finger Gloves, M","level":3}],[{"name":"Half-Finger Gloves, L","level":3}],[{"name":"Half-Finger Gloves, L","level":3}],[{"name":"Full-Finger Gloves, S","level":3}],[{"name":"Full-Finger Gloves, M","level":3}],[{"name":"Full-Finger Gloves, L","level":3}],[{"name":"Jerseys","level":2}],[{"name":"Long-Sleeve Logo Jersey, S","level":3}],[{"name":"Long-Sleeve Logo Jersey, M","level":3}],[{"name":"Long-Sleeve Logo Jersey, M","level":3}],[{"name":"Long-Sleeve Logo Jersey, M","level":3}],[{"name":"Long-Sleeve Logo Jersey, L","level":3}],[{"name":"Long-Sleeve Logo Jersey, L","level":3}],[{"name":"Long-Sleeve Logo Jersey, L","level":3}],[{"name":"Long-Sleeve Logo Jersey, XL","level":3}],[{"name":"Long-Sleeve Logo Jersey, XL","level":3}],[{"name":"Long-Sleeve Logo Jersey, XL","level":3}],[{"name":"Short-Sleeve Classic Jersey, S","level":3}],[{"name":"Short-Sleeve Classic Jersey, M","level":3}],[{"name":"Short-Sleeve Classic Jersey, L","level":3}],[{"name":"Short-Sleeve Classic Jersey, XL","level":3}],[{"name":"Shorts","level":2}],[{"name":"Men's Sports Shorts, S","level":3}],[{"name":"Men's Sports Shorts, M","level":3}],[{"name":"Men's Sports Shorts, L","level":3}],[{"name":"Women's Mountain Shorts, S","level":3}],[{"name":"Women's Mountain Shorts, M","level":3}],[{"name":"Women's Mountain Shorts, L","level":3}],[{"name":"Socks","level":2}],[{"name":"Mountain Bike Socks, M","level":3}],[{"name":"Mountain Bike Socks, L","level":3}],[{"name":"Racing Socks, M","level":3}],[{"name":"Racing Socks, L","level":3}],[{"name":"Tights","level":2}],[{"name":"Women's Tights, S","level":3}],[{"name":"Women's Tights, M","level":3}],[{"name":"Women's Tights, L","level":3}],[{"name":"Vests","level":2}],[{"name":"Classic Vest, S","level":3}],[{"name":"Classic Vest, M","level":3}],[{"name":"Classic Vest, L","level":3}],[{"name":"Components","level":1}],[{"name":"Bottom Brackets","level":2}],[{"name":"LL Bottom Bracket","level":3}],[{"name":"HL Bottom Bracket","level":3}],[{"name":"Brakes","level":2}],[{"name":"Rear Brakes","level":3}],[{"name":"Front Brakes","level":3}],[{"name":"Chains","level":2}],[{"name":"Chain","level":3}],[{"name":"Cranksets","level":2}],[{"name":"LL Crankset","level":3}],[{"name":"ML Crankset","level":3}],[{"name":"HL Crankset","level":3}],[{"name":"Derailleurs","level":2}],[{"name":"Rear Derailleur","level":3}],[{"name":"Front Derailleur","level":3}],[{"name":"Forks","level":2}],[{"name":"LL Fork","level":3}],[{"name":"HL Fork","level":3}],[{"name":"Handlebars","level":2}],[{"name":"LL Mountain Handlebars","level":3}],[{"name":"LL Mountain Handlebars","level":3}],[{"name":"ML Mountain Handlebars","level":3}],[{"name":"ML Mountain Handlebars","level":3}],[{"name":"HL Mountain Handlebars","level":3}],[{"name":"HL Mountain Handlebars","level":3}],[{"name":"LL Road Handlebars","level":3}],[{"name":"LL Road Handlebars","level":3}],[{"name":"HL Road Handlebars","level":3}],[{"name":"HL Road Handlebars","level":3}],[{"name":"LL Touring Handlebars","level":3}],[{"name":"HL Touring Handlebars","level":3}],[{"name":"Headsets","level":2}],[{"name":"LL Headset","level":3}],[{"name":"ML Headset","level":3}],[{"name":"HL Headset","level":3}],[{"name":"Mountain Frames","level":2}],[{"name":"HL Mountain Frame - Silver, 42","level":3}],[{"name":"HL Mountain Frame - Silver, 42","level":3}],[{"name":"HL Mountain Frame - Silver, 42","level":3}],[{"name":"HL Mountain Frame - Silver, 48","level":3}],[{"name":"HL Mountain Frame - Silver, 46","level":3}],[{"name":"HL Mountain Frame - Silver, 46","level":3}],[{"name":"HL Mountain Frame - Silver, 46","level":3}],[{"name":"HL Mountain Frame - Black, 42","level":3}],[{"name":"HL Mountain Frame - Black, 42","level":3}],[{"name":"HL Mountain Frame - Black, 42","level":3}],[{"name":"HL Mountain Frame - Black, 44","level":3}],[{"name":"HL Mountain Frame - Black, 48","level":3}],[{"name":"HL Mountain Frame - Black, 38","level":3}],[{"name":"HL Mountain Frame - Black, 38","level":3}],[{"name":"HL Mountain Frame - Black, 38","level":3}],[{"name":"HL Mountain Frame - Silver, 38","level":3}],[{"name":"HL Mountain Frame - Silver, 38","level":3}],[{"name":"HL Mountain Frame - Silver, 38","level":3}],[{"name":"ML Mountain Frame - Black, 38","level":3}],[{"name":"ML Mountain Frame - Black, 40","level":3}],[{"name":"ML Mountain Frame - Black, 44","level":3}],[{"name":"ML Mountain Frame - Black, 48","level":3}],[{"name":"ML Mountain Frame-W - Silver, 40","level":3}],[{"name":"ML Mountain Frame-W - Silver, 42","level":3}],[{"name":"ML Mountain Frame-W - Silver, 46","level":3}],[{"name":"LL Mountain Frame - Silver, 42","level":3}],[{"name":"LL Mountain Frame - Silver, 44","level":3}],[{"name":"LL Mountain Frame - Silver, 48","level":3}],[{"name":"LL Mountain Frame - Silver, 52","level":3}],[{"name":"LL Mountain Frame - Black, 42","level":3}],[{"name":"LL Mountain Frame - Black, 44","level":3}],[{"name":"LL Mountain Frame - Black, 48","level":3}],[{"name":"LL Mountain Frame - Black, 52","level":3}],[{"name":"ML Mountain Frame-W - Silver, 38","level":3}],[{"name":"LL Mountain Frame - Black, 40","level":3}],[{"name":"LL Mountain Frame - Silver, 40","level":3}],[{"name":"Pedals","level":2}],[{"name":"LL Mountain Pedal","level":3}],[{"name":"ML Mountain Pedal","level":3}],[{"name":"HL Mountain Pedal","level":3}],[{"name":"LL Road Pedal","level":3}],[{"name":"ML Road Pedal","level":3}],[{"name":"HL Road Pedal","level":3}],[{"name":"Touring Pedal","level":3}],[{"name":"Road Frames","level":2}],[{"name":"HL Road Frame - Red, 62","level":3}],[{"name":"HL Road Frame - Red, 62","level":3}],[{"name":"HL Road Frame - Red, 62","level":3}],[{"name":"HL Road Frame - Red, 44","level":3}],[{"name":"HL Road Frame - Red, 44","level":3}],[{"name":"HL Road Frame - Red, 44","level":3}],[{"name":"HL Road Frame - Red, 48","level":3}],[{"name":"HL Road Frame - Red, 48","level":3}],[{"name":"LL Road Frame - Black, 58","level":3}],[{"name":"LL Road Frame - Black, 58","level":3}],[{"name":"LL Road Frame - Black, 58","level":3}],[{"name":"LL Road Frame - Black, 60","level":3}],[{"name":"LL Road Frame - Black, 60","level":3}],[{"name":"LL Road Frame - Black, 60","level":3}],[{"name":"LL Road Frame - Red, 44","level":3}],[{"name":"LL Road Frame - Red, 44","level":3}],[{"name":"LL Road Frame - Red, 48","level":3}],[{"name":"LL Road Frame - Red, 48","level":3}],[{"name":"LL Road Frame - Red, 52","level":3}],[{"name":"LL Road Frame - Red, 52","level":3}],[{"name":"LL Road Frame - Red, 60","level":3}],[{"name":"LL Road Frame - Red, 60","level":3}],[{"name":"LL Road Frame - Red, 62","level":3}],[{"name":"LL Road Frame - Red, 62","level":3}],[{"name":"ML Road Frame - Red, 48","level":3}],[{"name":"ML Road Frame - Red, 52","level":3}],[{"name":"LL Road Frame - Black, 44","level":3}],[{"name":"LL Road Frame - Black, 44","level":3}],[{"name":"LL Road Frame - Black, 44","level":3}],[{"name":"LL Road Frame - Black, 52","level":3}],[{"name":"LL Road Frame - Black, 52","level":3}],[{"name":"LL Road Frame - Black, 52","level":3}],[{"name":"ML Road Frame-W - Yellow, 38","level":3}],[{"name":"ML Road Frame-W - Yellow, 38","level":3}],[{"name":"ML Road Frame-W - Yellow, 40","level":3}],[{"name":"ML Road Frame-W - Yellow, 40","level":3}],[{"name":"ML Road Frame-W - Yellow, 44","level":3}],[{"name":"ML Road Frame-W - Yellow, 44","level":3}],[{"name":"ML Road Frame-W - Yellow, 48","level":3}],[{"name":"ML Road Frame-W - Yellow, 48","level":3}],[{"name":"HL Road Frame - Black, 44","level":3}],[{"name":"HL Road Frame - Black, 44","level":3}],[{"name":"HL Road Frame - Black, 48","level":3}],[{"name":"HL Road Frame - Black, 48","level":3}],[{"name":"Saddles","level":2}],[{"name":"LL Mountain Seat\/Saddle","level":3}],[{"name":"ML Mountain Seat\/Saddle","level":3}],[{"name":"HL Mountain Seat\/Saddle","level":3}],[{"name":"LL Road Seat\/Saddle","level":3}],[{"name":"HL Road Seat\/Saddle","level":3}],[{"name":"LL Touring Seat\/Saddle","level":3}],[{"name":"ML Touring Seat\/Saddle","level":3}],[{"name":"HL Touring Seat\/Saddle","level":3}],[{"name":"Touring Frames","level":2}],[{"name":"HL Touring Frame - Yellow, 60","level":3}],[{"name":"LL Touring Frame - Yellow, 62","level":3}],[{"name":"HL Touring Frame - Yellow, 46","level":3}],[{"name":"HL Touring Frame - Yellow, 50","level":3}],[{"name":"HL Touring Frame - Yellow, 54","level":3}],[{"name":"HL Touring Frame - Blue, 46","level":3}],[{"name":"HL Touring Frame - Blue, 50","level":3}],[{"name":"HL Touring Frame - Blue, 54","level":3}],[{"name":"HL Touring Frame - Blue, 60","level":3}],[{"name":"LL Touring Frame - Blue, 50","level":3}],[{"name":"LL Touring Frame - Blue, 54","level":3}],[{"name":"LL Touring Frame - Blue, 58","level":3}],[{"name":"LL Touring Frame - Blue, 62","level":3}],[{"name":"LL Touring Frame - Yellow, 44","level":3}],[{"name":"LL Touring Frame - Yellow, 50","level":3}],[{"name":"LL Touring Frame - Yellow, 58","level":3}],[{"name":"LL Touring Frame - Blue, 44","level":3}],[{"name":"Wheels","level":2}],[{"name":"LL Mountain Front Wheel","level":3}],[{"name":"ML Mountain Front Wheel","level":3}],[{"name":"HL Mountain Front Wheel","level":3}],[{"name":"ML Road Front Wheel","level":3}],[{"name":"HL Road Front Wheel","level":3}],[{"name":"LL Mountain Rear Wheel","level":3}],[{"name":"ML Mountain Rear Wheel","level":3}],[{"name":"HL Mountain Rear Wheel","level":3}],[{"name":"LL Road Rear Wheel","level":3}],[{"name":"ML Road Rear Wheel","level":3}],[{"name":"HL Road Rear Wheel","level":3}]],"colsInfo":["[Date].[Calendar Year]","[Measures]"],"cols":[[{"name":"All","level":0},{"name":"Total Sales Amount","level":0}],[{"name":"CY 2005","level":1},{"name":"Total Sales Amount","level":0}],[{"name":"CY 2006","level":1},{"name":"Total Sales Amount","level":0}],[{"name":"CY 2007","level":1},{"name":"Total Sales Amount","level":0}],[{"name":"CY 2008","level":1},{"name":"Total Sales Amount","level":0}]],"cells":[[109809274.203,11331808.9619,30674773.1804,41993729.722901,25808962.337801],[1272057.8878,20235.3646,92735.3534,590242.5866,568844.5832],[237096.156,0,0,134868.468,102227.688],[237096.156,0,0,134868.468,102227.688],[39591,0,0,18921,20670],[39591,0,0,18921,20670],[64274.793600001,0,0,27761.6021,36513.1915],[28654.163600001,0,0,13173.9121,15480.2515],[20229.75,0,0,8231.76,11997.99],[15390.88,0,0,6355.93,9034.95],[18406.9725,0,0,9777.9388,8629.0337],[18406.9725,0,0,9777.9388,8629.0337],[46619.580000001,0,0,19408.34,27211.24],[46619.580000001,0,0,19408.34,27211.24],[484048.5323,20235.3646,74281.3921,206027.1962,183504.5794],[11385.186,6439.4935,4945.6925,0,0],[29031.3507,0,18023.9355,11007.4152,0],[117355.8586,0,0,55777.0171,61578.8415],[12098.0788,6681.7315,5416.3473,0,0],[31866.8299,0,19449.1622,12417.6677,0],[116904.6102,0,0,57164.654,59739.9562],[13331.5816,7114.1396,6217.442,0,0],[33795.2635,0,20228.8126,13566.4509,0],[118279.773,0,0,56093.9913,62185.7817],[105826.4185,0,0,58303.9119,47522.5066],[105826.4185,0,0,58303.9119,47522.5066],[16225.22,0,10084.7,6140.52,0],[16225.22,0,10084.7,6140.52,0],[13514.6873,0,8369.2613,5145.426,0],[13514.6873,0,8369.2613,5145.426,0],[246454.5276,0,0,103888.1836,142566.344],[8232.5975999999,0,0,3733.6636,4498.934],[15444.049999999,0,0,6551.87,8892.18],[9480.2399999996,0,0,3986.01,5494.23],[7425.1199999998,0,0,2949.09,4476.03],[21541.38,0,0,9071.37,12470.01],[34818.390000001,0,0,14995,19823.39],[48860,0,0,20300,28560],[22435.56,0,0,9369.64,13065.92],[23140.74,0,0,9821.07,13319.67],[27970.8,0,0,12877,15093.8],[27105.65,0,0,10233.47,16872.18],[94620526.2077,10661722.2832,26486358.2005,34910877.6904,22561568.0336],[36445443.9409,5131309.7787,10753294.8536,12843901.5087,7716937.7999001],[1291868.701,688157.976,603710.725,0,0],[1186494.8505,592814.0964,593680.7541,0,0],[1217210.3605,629139.5896,588070.7709,0,0],[1019657.0012,503198.52,516458.4812,0,0],[1339997.2548,700113.3256,639883.9292,0,0],[1254722.7326,660893.2418,593829.4908,0,0],[1365852.3783,733294.8773,632557.501,0,0],[1234276.0309,623698.152,610577.8789,0,0],[1532696.428,0,764614.0228,768082.4052,0],[2160981.5974,0,0,1024359.1046,1136622.4928],[1523931.0089,0,859725.3282,664205.6807,0],[1914547.8517,0,0,903061.6755,1011486.1762],[1528008.3906,0,806696.9858,721311.4048,0],[1906248.5514,0,0,877077.7875,1029170.7639],[1811229.023,0,896511.5976,914717.4254,0],[2589363.7774,0,0,1261406.3697,1327957.4077],[1744009.3828,0,934918.0495,809091.3333,0],[2265485.3791,0,0,1126055.8919,1139429.4872],[1352144.9725,0,682499.6876,669645.2849,0],[1957528.2445,0,0,946453.876,1011074.3685],[442477.087,0,230310.4595,212166.6275,0],[501648.8751,0,278262.0155,223386.8596,0],[484051.518,0,261789.576,222261.942,0],[479071.9001,0,259197.6,219874.3001,0],[241773.758,0,0,110806.56,130967.198],[323703.8207,0,0,166266.1667,157437.654],[217457.874,0,0,97417.434,120040.44],[227347.6673,0,0,100227.9193,127119.748],[145089.432,0,0,98986.248,46103.184],[141360.498,0,0,93562.344,47798.154],[122512.4316,0,0,80793.57,41718.8616],[142897.2708,0,0,96274.296,46622.9748],[161293.3452,0,0,102263.19,59030.1552],[101734.116,0,0,50003.074,51731.042],[136293.476,0,0,84130.442,52163.034],[125925.668,0,0,70522.694,55402.974],[157569.082,0,0,85210.422,72358.66],[96982.204,0,0,44279.18,52703.024],[43878790.997,5530412.5045,15733063.3469,15246410.5797,7368904.5659001],[1769096.688,828011.678,941085.01,0,0],[1340419.942,612599.824,727820.118,0,0],[1540803.062,659117.334,881685.728,0,0],[1415563.612,583973.664,831589.948,0,0],[1847818.628,868803.956,979014.672,0,0],[507978.2959,245218.1717,262760.1242,0,0],[306177.9,140841.834,165336.066,0,0],[302678.724,137342.658,165336.066,0,0],[136467.864,45489.288,90978.576,0,0],[621103.74,307927.488,313176.252,0,0],[79137.9131,27824.1073,51313.8058,0,0],[224874.728,0,119014.48,105860.248,0],[306940.7292,154360.8756,152579.8536,0,0],[703387.0086,0,379189.3727,324197.6359,0],[252374.4387,118706.8688,133667.5699,0,0],[621815.9716,0,327486.8986,294329.073,0],[311098.6849,150445.9257,160652.7592,0,0],[626604.3469,0,293370.3799,333233.967,0],[253492.9961,117029.0334,136463.9627,0,0],[624046.162,0,327401.8659,296644.2961,0],[149047.7298,64177.212,84870.5178,0,0],[374582.416,0,196530.49,178051.926,0],[247480.7516,117308.6727,130172.0789,0,0],[618769.5141,0,324143.5313,294625.9828,0],[153382.1387,64876.3102,88505.8285,0,0],[368516.1227,0,194848.9407,173667.182,0],[88785.4679,36632.7444,52152.7235,0,0],[223465.346,0,124652.008,98813.338,0],[146391.1568,65435.5888,80955.568,0,0],[362853.8522,0,195747.5,167106.3522,0],[87387.2714,27824.1071,59563.1643,0,0],[222995.552,0,119954.068,103041.484,0],[316911.2711,156465.1628,160446.1083,0,0],[723179.7431,0,385607.5417,337572.2014,0],[1448122.479,0,782553.939,665568.54,0],[1343481.8615,0,739485.7415,603996.12,0],[1066766.61,0,623542.92,443223.69,0],[824194.3125,0,460746,363448.3125,0],[762813.87,0,0,390447.33,372366.54],[1256577.3849,0,681953.8224,574623.5625,0],[1260279.93,0,0,705639.48,554640.45],[1149797.7519,0,649347.3144,500450.4375,0],[1197858.2015,0,0,669117.2615,528740.94],[1037551.125,0,611273.8125,426277.3125,0],[974896.65,0,0,578096.61,396800.04],[763110.5625,0,396171.75,366938.8125,0],[743267.07,0,0,379696.59,363570.48],[535907.5582,0,282196.6082,253710.95,0],[692002.5227,0,0,342409.6427,349592.88],[466203.875,0,243106.3125,223097.5625,0],[605087.9062,0,0,292695.2942,312392.612],[373363.275,0,206290.2125,167073.0625,0],[558676.314,0,0,277657.422,281018.892],[283523.9875,0,129256.525,154267.4625,0],[434301.924,0,0,202584.592,231717.332],[536593.8586,0,289064.8114,247529.0472,0],[697345.0191,0,0,341253.2971,356091.722],[1657198.1825,0,0,816227.5358,840970.6467],[1120066.3643,0,0,535284.373,584781.9913],[694003.92,0,0,294611.468,399392.452],[1774883.5572,0,0,877665.5937,897217.9635],[361145.312,0,0,174632.766,186512.546],[290298.624,0,0,130029.592,160269.032],[578174.313,0,0,291373.6361,286800.6769],[515666.9065,0,0,249639.537,266027.3695],[14296291.2698,0,0,6820565.602,7475725.6678],[635723.7159,0,0,334440.9159,301282.8],[1426372.8694,0,0,621336.3234,805036.546],[981187.8492,0,0,420931.3992,560256.45],[667158.1488,0,0,269495.2728,397662.876],[1518133.1013,0,0,691991.814,826141.2873],[290075.1193,0,0,140268.8893,149806.23],[210946.177,0,0,101672.257,109273.92],[135284.0088,0,0,55258.6788,80025.33],[358121.8901,0,0,173097.3883,185024.5018],[291747.2629,0,0,143128.7929,148618.47],[196809.977,0,0,96741.197,100068.78],[130898.5762,0,0,60523.7962,70374.78],[351547.7127,0,0,170188.0445,181359.6682],[1586953.5731,0,0,776244.8478,810708.7253],[1071401.058,0,0,533078.052,538323.006],[743353.026,0,0,333769.8,409583.226],[1721242.5144,0,0,885952.3585,835290.1559],[438867.4781,0,0,234286.7381,204580.74],[286218.66,0,0,129745.98,156472.68],[772302.0123,0,0,409727.1142,362574.8981],[133365.0342,0,0,62990.2542,70374.78],[348581.5051,0,0,175695.6879,172885.8172],[2117613.4491,34376.3353,485587.1546,1010112.1566,587537.8026],[166739.7086,0,101862.7138,64876.9948,0],[46980.3954,0,26786.6394,20193.756,0],[85581.1112,0,52236.6124,33344.4988,0],[34178.202,0,22839.462,11338.74,0],[51229.4461,2686.8726,9387.6138,21757.1017,17397.858],[5081.0472,2686.8726,2394.1746,0,0],[11698.7968,0,6993.4392,4705.3576,0],[34449.6021,0,0,17051.7441,17397.858],[242795.8742,0,88796.0615,116384.7595,37615.0532],[7338.0981,0,3970.2209,3367.8772,0],[29152.4529,0,0,16729.8416,12422.6113],[14871.0972,0,7927.0369,6944.0603,0],[39674.3903,0,0,23156.3064,16518.0839],[4210.4122,0,2543.202,1667.2102,0],[18701.8473,0,0,10027.4893,8674.358],[11237.442,0,6997.758,4239.684,0],[47987.9352,0,27707.7335,20280.2017,0],[69622.199,0,39650.1102,29972.0888,0],[752259.3884,28255.5726,110243.769,360375.1941,253384.8527],[21445.71,0,0,7448.51,13997.2],[12603.2548,6316.0476,6287.2072,0,0],[35500.8718,0,22674.5089,12826.3629,0],[67145.0884,0,0,37398.4189,29746.6695],[28399.4946,14758.2654,13641.2292,0,0],[66166.1226,0,39992.075,26174.0476,0],[104189.3582,0,0,59874.6928,44314.6654],[13670.3496,7181.2596,6489.09,0,0],[31612.0151,0,21159.6587,10452.3564,0],[50328.8323,0,0,28033.2923,22295.54],[71606.0732,0,0,41865.5521,29740.5211],[21973.93,0,0,9664.21,12309.72],[98472.7173,0,0,55057.4579,43415.2594],[129145.5705,0,0,71580.2932,57565.2773],[413522.527,0,49261.5685,209746.975,154513.9835],[20364.9973,0,11063.4038,9301.5935,0],[45516.2968,0,27651.9227,17864.3741,0],[16017.33,0,10546.242,5471.088,0],[137164.1277,0,0,73062.0854,64102.0423],[57685.758,0,0,30389.658,27296.1],[136774.0172,0,0,73658.176,63115.8412],[29745.1281,3433.8901,3139.4983,13023.2756,10148.4641],[6060.3884,3057.6901,3002.6983,0,0],[513,376.2,136.8,0,0],[9387.1494,0,0,5427.5794,3959.57],[13784.5903,0,0,7595.6962,6188.8941],[201833.006,0,122895.9297,78937.0763,0],[90550.9053,0,56129.6253,34421.28,0],[17727.636,0,12508.332,5219.304,0],[93554.4647,0,54257.9724,39296.4923,0],[259488.3707,0,0,145010.7796,114477.5911],[156398.0697,0,0,86755.9998,69642.0699],[90250.601,0,0,53543.0798,36707.5212],[12839.7,0,0,4711.7,8128],[11799076.6584,615474.9788,3610092.4719,5482497.2893,2091011.9184],[51826.374,0,0,30792.822,21033.552],[12244.932,0,0,8195.682,4049.25],[39581.442,0,0,22597.14,16984.302],[66018.711,0,0,45187.311,20831.4],[15719.4,0,0,13610.7,2108.7],[50299.311,0,0,31576.611,18722.7],[9377.7102,0,0,5685.9342,3691.776],[9377.7102,0,0,5685.9342,3691.776],[203942.6182,0,0,124249.2742,79693.344],[44855.244,0,0,26639.382,18215.862],[10464.792,0,0,10464.792,0],[148622.5822,0,0,87145.1002,61477.482],[70209.4958,0,0,44321.133,25888.3628],[25725.228,0,0,17417.364,8307.864],[44484.2678,0,0,26903.769,17580.4988],[77931.6896,0,49672.6196,28259.07,0],[16897.08,0,12183.684,4713.396,0],[61034.6096,0,37488.9356,23545.674,0],[170591.3209,0,53642.6958,88710.9931,28237.632],[10203.69,0,6705.282,3498.408,0],[11804.5787,0,0,7047.7067,4756.872],[25761.0274,0,15244.7287,10516.2987,0],[25992.6785,0,0,15887.3345,10105.344],[17056.468,0,12529.9438,4526.5242,0],[17318.88,0,0,12844.836,4474.044],[2696.6895,0,2696.6895,0,0],[2725.848,0,0,2725.848,0],[21386.1868,0,16466.0518,4920.135,0],[22009.41,0,0,16019.964,5989.446],[1548.624,0,0,1548.624,0],[12087.24,0,0,9175.314,2911.926],[60942.1984,0,35931.8372,25010.3612,0],[1949.4,0,1949.4,0,0],[39909.1084,0,23205.7652,16703.3432,0],[19083.69,0,10776.672,8307.018,0],[4713672.1469,371587.7928,1400331.6836,2067908.6445,873844.026],[17342.2776,9393.7337,7948.5439,0,0],[119083.632,0,105686.7234,13396.9086,0],[133448.1,0,0,105612.3,27835.8],[141635.1,69589.5,72045.6,0,0],[91769.5523,51304.2379,40465.3144,0,0],[195743.7201,0,107175.2688,88568.4513,0],[212043.3,0,0,119530.2,92513.1],[126502.6611,62179.2741,64323.387,0,0],[379114.9325,0,226732.814,152382.1185,0],[395972.64,0,0,234830.4,161142.24],[13765.92,7287.84,6478.08,0,0],[106078.56,57492.96,48585.6,0,0],[92196.8547,50029.301,42167.5537,0,0],[195814.703,0,106004.952,89809.751,0],[213776.64,0,0,118224.96,95551.68],[130789.6769,64310.9461,66478.7308,0,0],[387021.804,0,232213.0824,154808.7216,0],[412969.1998,0,0,249229.1998,163740],[107557.584,0,59010.192,48547.392,0],[14229.408,0,14229.408,0,0],[129529.464,0,80145.048,49384.416,0],[200026.4154,0,120641.3852,79385.0302,0],[195826.3891,0,0,119585.9431,76240.446],[136970.658,0,0,78424.986,58545.672],[41069.352,0,0,34952.64,6116.712],[100569.3572,0,0,57951.6872,42617.67],[58777.53,0,0,39607.5,19170.03],[6970.92,0,0,6970.92,0],[67332.75,0,0,43568.25,23764.5],[63396.702,0,0,41515.098,21881.604],[93584.423,0,0,53418.191,40166.232],[57851.364,0,0,39117.114,18734.25],[2248.11,0,0,2248.11,0],[1529.178,0,0,1529.178,0],[1198.992,0,0,1198.992,0],[69934.2762,0,0,44110.1862,25824.09],[147483.9098,0,0,94060.5253,53423.3845],[10908.006,0,0,7774.08,3133.926],[12852.63,0,0,9313.5,3539.13],[38018.3258,0,0,22721.4853,15296.8405],[21087.192,0,0,12608.586,8478.606],[24624.894,0,0,15013.362,9611.532],[32849.544,0,0,20020.728,12828.816],[7143.318,0,0,6608.784,534.534],[3849853.3438,243887.186,1618391.5119,1631377.2719,356197.374],[22742.277,9854.9867,12887.2903,0,0],[192862.0954,0,152259.549,40602.5464,0],[178651.2,0,0,141718.5,36932.7],[20468.0493,8338.8349,12129.2144,0,0],[195204.55,0,154602.0036,40602.5464,0],[179510.1,0,0,141718.5,37791.6],[37479.2736,0,37479.2736,0,0],[52392.9,0,0,52392.9,0],[34108.9328,19286.7264,14822.2064,0,0],[80197.0552,0,52054.5106,28142.5446,0],[63329.916,0,0,42489.72,20840.196],[178.5808,178.5808,0,0,0],[12323.8594,0,12323.8594,0,0],[12342.252,0,0,12342.252,0],[55733.2746,31821.3086,23911.966,0,0],[138959.3245,0,91613.6365,47345.688,0],[37339.4546,20049.2638,17290.1908,0,0],[94286.712,0,59283.276,35003.436,0],[1287.5674,919.691,367.8764,0,0],[18816.876,0,16995.888,1820.988,0],[56836.9038,31453.4322,25383.4716,0,0],[138597.42,0,91454.064,47143.356,0],[37891.2692,20601.0784,17290.1908,0,0],[98823.1303,0,60699.6,38123.5303,0],[89224.5,48895.026,40329.474,0,0],[32120.82,19629.39,12491.43,0,0],[4643.1008,2321.5504,2321.5504,0,0],[23728.0278,0,18209.8818,5518.146,0],[16793.556,0,0,16186.56,606.996],[54109.9824,30537.3168,23572.6656,0,0],[126258.9816,0,83401.381,42857.6006,0],[119226.5589,0,0,79367.1549,39859.404],[160928.5392,0,98958.0735,61970.4657,0],[142402.302,0,0,88510.704,53891.598],[42827.7564,0,34716.4389,8111.3175,0],[25339.758,0,0,25339.758,0],[255122.1328,0,165248.7349,89873.3979,0],[230578.4141,0,0,156700.5281,73877.886],[159955.1811,0,97335.81,62619.3711,0],[141331.608,0,0,86726.214,54605.394],[192081.2772,0,151478.7308,40602.5464,0],[182945.7,0,0,145154.1,37791.6],[37479.2736,0,37479.2736,0,0],[52392.9,0,0,52392.9,0],[55829.3882,0,0,37831.9631,17997.4251],[5636.9571,0,0,3840.192,1796.7651],[12497.1671,0,0,7847.3351,4649.832],[16392.096,0,0,10454.304,5937.792],[162.72,0,0,162.72,0],[4232.256,0,0,3663.744,568.512],[1480.752,0,0,1480.752,0],[1972.656,0,0,1855.236,117.42],[13454.784,0,0,8527.68,4927.104],[1642327.6862,0,0,1032154.0442,610173.642],[232378.2602,0,0,133593.5162,98784.744],[69127.1351,0,0,39719.4911,29407.644],[52404.102,0,0,39754.836,12649.266],[49994.718,0,0,42766.566,7228.152],[323268.2559,0,0,199184.9799,124083.276],[68667.444,0,0,48790.026,19877.418],[74690.904,0,0,53608.794,21082.11],[324333.1033,0,0,200249.8273,124083.276],[221720.9525,0,0,130164.3605,91556.592],[63216.432,0,0,38810.088,24406.344],[42210.972,0,0,24806.448,17404.524],[800.208,0,0,800.208,0],[3000.78,0,0,3000.78,0],[58699.3912,0,0,38294.0872,20405.304],[45611.856,0,0,26406.864,19204.992],[7201.872,0,0,7201.872,0],[5001.3,0,0,5001.3,0],[679070.0654,0,452122.1238,226947.9416,0],[22462.845,0,14736.081,7726.764,0],[33360.39,0,24706.755,8653.635,0],[39988.638,0,32603.349,7385.289,0],[78986.43,0,56482.749,22503.681,0],[112286.412,0,77432.076,34854.336,0],[18005.274,0,14372.631,3632.643,0],[119193.5227,0,70001.0034,49192.5193,0],[166013.2837,0,98071.1784,67942.1053,0],[58488.774,0,33431.805,25056.969,0],[10574.784,0,10574.784,0,0],[19709.712,0,19709.712,0,0]]}
	